django_polls_dlt/__init__.py
django_polls_dlt/admin.py
django_polls_dlt/apps.py
django_polls_dlt/models.py
django_polls_dlt/tests.py
django_polls_dlt/urls.py
django_polls_dlt/views.py
django_polls_dlt/migrations/0001_initial.py
django_polls_dlt/migrations/__init__.py
django_polls_dlt/static/.DS_Store
django_polls_dlt/static/polls/.DS_Store
django_polls_dlt/static/polls/style.css
django_polls_dlt/static/polls/images/background.jpg
django_polls_dlt/templates/polls/detail.html
django_polls_dlt/templates/polls/index.html
django_polls_dlt/templates/polls/results.html
django_polls_dlt/templates/polls/v2/detail.html
django_polls_dlt/templates/polls/v2/index.html
django_polls_dlt/templates/polls/v2/results.html
django_polls_dlt-0.1.dist-info/LICENSE
django_polls_dlt-0.1.dist-info/METADATA
django_polls_dlt-0.1.dist-info/WHEEL
django_polls_dlt-0.1.dist-info/top_level.txt
django_polls_dlt-0.1.dist-info/RECORD
